rover_arm/.DS_Store
rover_arm/__init__.py
rover_arm/keyboard_control.py
rover_arm/sample.py
rover_arm/data/panda.urdf
rover_arm/data/rover_arm.xml
rover_arm/data/meshes/.DS_Store
rover_arm/data/meshes/collision/finger.obj
rover_arm/data/meshes/collision/hand.obj
rover_arm/data/meshes/collision/link0.obj
rover_arm/data/meshes/collision/link1.obj
rover_arm/data/meshes/collision/link2.obj
rover_arm/data/meshes/collision/link3.obj
rover_arm/data/meshes/collision/link4.obj
rover_arm/data/meshes/collision/link5.obj
rover_arm/data/meshes/collision/link6.mtl
rover_arm/data/meshes/collision/link6.obj
rover_arm/data/meshes/collision/link7.obj
rover_arm/data/meshes/visual/colors.png
rover_arm/data/meshes/visual/finger.mtl
rover_arm/data/meshes/visual/finger.obj
rover_arm/data/meshes/visual/hand.mtl
rover_arm/data/meshes/visual/hand.obj
rover_arm/data/meshes/visual/link1.mtl
rover_arm/data/meshes/visual/link1.obj
rover_arm/data/meshes/visual/link2.mtl
rover_arm/data/meshes/visual/link2.obj
rover_arm/data/meshes/visual/link3.mtl
rover_arm/data/meshes/visual/link3.obj
rover_arm/data/meshes/visual/link4.mtl
rover_arm/data/meshes/visual/link4.obj
rover_arm/data/meshes/visual/link5.mtl
rover_arm/data/meshes/visual/link5.obj
rover_arm/data/meshes/visual/link6.mtl
rover_arm/data/meshes/visual/link6.obj
rover_arm/envs/__init__.py
rover_arm/envs/roverarm_env.py
rover_arm/envs/roverarm_env_arrange.py
rover_arm/envs/roverarm_env_gym.py
rover_arm/envs/roverarm_env_place.py
rover_arm/envs/__pycache__/__init__.cpython-39.pyc
rover_arm/envs/__pycache__/roverarm_env.cpython-39.pyc
rover_arm-1.1.11.dist-info/METADATA
rover_arm-1.1.11.dist-info/WHEEL
rover_arm-1.1.11.dist-info/top_level.txt
rover_arm-1.1.11.dist-info/RECORD
