Metadata-Version: 2.1
Name: rover-arm
Version: 1.1.11
Summary: A OpenAI Gym Env for Rover with Arm
Author: Sai Phani
Requires-Dist: gymnasium
Requires-Dist: pybullet
Requires-Dist: gym
Provides-Extra: dev
Requires-Dist: pynput ; extra == 'dev'
